{
  "type": "slashblade:shaped_blade",
  "blade": "last_smith:oboro_muramasa",
  "category": "equipment",
  "key": {
    "C": {
      "type": "slashblade:blade",
      "item": "slashblade:slashblade",
      "request": {
        "kill": 1500,
        "name": "last_smith:muramasa_kagura",
        "proud_soul": 5000,
        "refine": 20
      }
    },
    "D": {
      "item": "slashblade:proudsoul_sphere"
    },
    "F": {
      "item": "last_smith:sakura_full"
    },
    "S": {
      "item": "last_smith:scroll_muramasa"
    },
    "U": {
      "type": "slashblade:blade",
      "item": "slashblade:slashblade",
      "request": {
        "kill": 1500,
        "name": "slashblade:muramasa",
        "proud_soul": 5000,
        "refine": 20
      }
    }
  },
  "pattern": [
    "DFD",
    "CSU",
    "DFD"
  ],
  "result": {
    "item": "slashblade:slashblade"
  },
  "show_notification": true
}